flask_mcp/__init__.py
flask_mcp/handler.py
flask_mcp/json_schema.py
flask_mcp/jsonrpc.py
flask_mcp/prompt.py
flask_mcp/resource.py
flask_mcp/server.py
flask_mcp/streamable_http.py
flask_mcp/tool.py
flask_mcp/types.py
flask_mcp_core-0.1.0.dist-info/METADATA
flask_mcp_core-0.1.0.dist-info/WHEEL
flask_mcp_core-0.1.0.dist-info/licenses/LICENSE
flask_mcp_core-0.1.0.dist-info/RECORD
