Metadata-Version: 2.4
Name: flask-mcp-core
Version: 0.1.0
Summary: Flask integration for Model Context Protocol (MCP)
Project-URL: Homepage, https://github.com/maocatooo/flask-mcp
Project-URL: Documentation, https://github.com/maocatooo/flask-mcp#readme
Project-URL: Repository, https://github.com/maocatooo/flask-mcp
Project-URL: Issues, https://github.com/maocatooo/flask-mcp/issues
Author-email: maocat <maocatzk@gmail.com>
License: Apache-2.0
License-File: LICENSE
Keywords: flask,mcp,model-context-protocol
Classifier: Development Status :: 3 - Alpha
Classifier: Framework :: Flask
Classifier: Intended Audience :: Developers
Classifier: License :: OSI Approved :: Apache Software License
Classifier: Programming Language :: Python :: 3
Classifier: Programming Language :: Python :: 3.9
Requires-Python: >=3.9
Requires-Dist: flask>=3
Requires-Dist: pydantic>=2
Provides-Extra: dev
Requires-Dist: black>=23.0.0; extra == 'dev'
Requires-Dist: pytest-cov>=4.0.0; extra == 'dev'
Requires-Dist: pytest>=7.0.0; extra == 'dev'
Requires-Dist: ruff>=0.1.0; extra == 'dev'
